[
  {
    "id": 1,
    "priority": 1,
    "action": { "type": "block" },
    "condition": {
      "urlFilter": "*://*.doubleclick.net/*",
      "excludedResourceTypes": ["main_frame"]
    }
  },
  {
    "id": 2,
    "priority": 1,
    "action": { "type": "block" },
    "condition": {
      "urlFilter": "*://*.googleadservices.com/*",
      "excludedResourceTypes": ["main_frame"]
    }
  },
  {
    "id": 3,
    "priority": 1,
    "action": { "type": "block" },
    "condition": {
      "urlFilter": "*://*.googlesyndication.com/*",
      "excludedResourceTypes": ["main_frame"]
    }
  },
  {
    "id": 4,
    "priority": 1,
    "action": { "type": "block" },
    "condition": {
      "urlFilter": "*://*.moat.com/*",
      "excludedResourceTypes": ["main_frame"]
    }
  },
  {
    "id": 5,
    "priority": 1,
    "action": { "type": "block" },
    "condition": {
      "urlFilter": "*://*.moatads.com/*",
      "excludedResourceTypes": ["main_frame"]
    }
  },
  {
    "id": 6,
    "priority": 1,
    "action": { "type": "block" },
    "condition": {
      "urlFilter": "*://*.google-analytics.com/*",
      "excludedResourceTypes": ["main_frame"]
    }
  },
  {
    "id": 7,
    "priority": 1,
    "action": { "type": "block" },
    "condition": {
      "urlFilter": "*://*.googletagmanager.com/*",
      "excludedResourceTypes": ["main_frame"]
    }
  },
  {
    "id": 8,
    "priority": 1,
    "action": { "type": "block" },
    "condition": {
      "urlFilter": "*://*.googletagservices.com/*",
      "excludedResourceTypes": ["main_frame"]
    }
  },
  {
    "id": 9,
    "priority": 1,
    "action": { "type": "block" },
    "condition": {
      "urlFilter": "*://*.2mdn.net/*",
      "excludedResourceTypes": ["main_frame"]
    }
  },
  {
    "id": 10,
    "priority": 1,
    "action": { "type": "block" },
    "condition": {
      "urlFilter": "*://*.app-measurement.com/*",
      "excludedResourceTypes": ["main_frame"]
    }
  },
  {
    "id": 11,
    "priority": 1,
    "action": { "type": "block" },
    "condition": {
      "urlFilter": "*://*.amazon-adsystem.com/*",
      "excludedResourceTypes": ["main_frame"]
    }
  },
  {
    "id": 12,
    "priority": 1,
    "action": { "type": "block" },
    "condition": {
      "urlFilter": "*://*.connect.facebook.net/*",
      "excludedResourceTypes": ["main_frame"]
    }
  },
  {
    "id": 13,
    "priority": 1,
    "action": { "type": "block" },
    "condition": {
      "urlFilter": "*://*.facebook.com/tr/*",
      "excludedResourceTypes": ["main_frame"]
    }
  },
  {
    "id": 14,
    "priority": 1,
    "action": { "type": "block" },
    "condition": {
      "urlFilter": "*://snap.licdn.com/*",
      "excludedResourceTypes": ["main_frame"]
    }
  },
  {
    "id": 15,
    "priority": 1,
    "action": { "type": "block" },
    "condition": {
      "urlFilter": "*://px.ads.linkedin.com/*",
      "excludedResourceTypes": ["main_frame"]
    }
  },
  {
    "id": 16,
    "priority": 1,
    "action": { "type": "block" },
    "condition": {
      "urlFilter": "*://bat.bing.com/*",
      "excludedResourceTypes": ["main_frame"]
    }
  },
  {
    "id": 17,
    "priority": 1,
    "action": { "type": "block" },
    "condition": {
      "urlFilter": "*://*.clarity.ms/*",
      "excludedResourceTypes": ["main_frame"]
    }
  },
  {
    "id": 18,
    "priority": 1,
    "action": { "type": "block" },
    "condition": {
      "urlFilter": "*://static.ads-twitter.com/*",
      "excludedResourceTypes": ["main_frame"]
    }
  },
  {
    "id": 19,
    "priority": 1,
    "action": { "type": "block" },
    "condition": {
      "urlFilter": "*://*.analytics.tiktok.com/*",
      "excludedResourceTypes": ["main_frame"]
    }
  },
  {
    "id": 20,
    "priority": 1,
    "action": { "type": "block" },
    "condition": {
      "urlFilter": "*://tr.snapchat.com/*",
      "excludedResourceTypes": ["main_frame"]
    }
  },
  {
    "id": 21,
    "priority": 1,
    "action": { "type": "block" },
    "condition": {
      "urlFilter": "*://ct.pinterest.com/*",
      "excludedResourceTypes": ["main_frame"]
    }
  },
  {
    "id": 22,
    "priority": 1,
    "action": { "type": "block" },
    "condition": {
      "urlFilter": "*://events.reddit.com/*",
      "excludedResourceTypes": ["main_frame"]
    }
  },
  {
    "id": 23,
    "priority": 1,
    "action": { "type": "block" },
    "condition": {
      "urlFilter": "*://*.criteo.com/*",
      "excludedResourceTypes": ["main_frame"]
    }
  },
  {
    "id": 24,
    "priority": 1,
    "action": { "type": "block" },
    "condition": {
      "urlFilter": "*://*.criteo.net/*",
      "excludedResourceTypes": ["main_frame"]
    }
  },
  {
    "id": 25,
    "priority": 1,
    "action": { "type": "block" },
    "condition": {
      "urlFilter": "*://*.taboola.com/*",
      "excludedResourceTypes": ["main_frame"]
    }
  },
  {
    "id": 26,
    "priority": 1,
    "action": { "type": "block" },
    "condition": {
      "urlFilter": "*://*.outbrain.com/*",
      "excludedResourceTypes": ["main_frame"]
    }
  },
  {
    "id": 27,
    "priority": 1,
    "action": { "type": "block" },
    "condition": {
      "urlFilter": "*://*.scorecardresearch.com/*",
      "excludedResourceTypes": ["main_frame"]
    }
  },
  {
    "id": 28,
    "priority": 1,
    "action": { "type": "block" },
    "condition": {
      "urlFilter": "*://*.quantserve.com/*",
      "excludedResourceTypes": ["main_frame"]
    }
  },
  {
    "id": 29,
    "priority": 1,
    "action": { "type": "block" },
    "condition": {
      "urlFilter": "*://*.adsrvr.org/*",
      "excludedResourceTypes": ["main_frame"]
    }
  },
  {
    "id": 30,
    "priority": 1,
    "action": { "type": "block" },
    "condition": {
      "urlFilter": "*://*.adnxs.com/*",
      "excludedResourceTypes": ["main_frame"]
    }
  },
  {
    "id": 31,
    "priority": 1,
    "action": { "type": "block" },
    "condition": {
      "urlFilter": "*://*.rubiconproject.com/*",
      "excludedResourceTypes": ["main_frame"]
    }
  },
  {
    "id": 32,
    "priority": 1,
    "action": { "type": "block" },
    "condition": {
      "urlFilter": "*://*.openx.net/*",
      "excludedResourceTypes": ["main_frame"]
    }
  },
  {
    "id": 33,
    "priority": 1,
    "action": { "type": "block" },
    "condition": {
      "urlFilter": "*://*.pubmatic.com/*",
      "excludedResourceTypes": ["main_frame"]
    }
  },
  {
    "id": 34,
    "priority": 1,
    "action": { "type": "block" },
    "condition": {
      "urlFilter": "*://*.indexww.com/*",
      "excludedResourceTypes": ["main_frame"]
    }
  },
  {
    "id": 35,
    "priority": 1,
    "action": { "type": "block" },
    "condition": {
      "urlFilter": "*://*.lijit.com/*",
      "excludedResourceTypes": ["main_frame"]
    }
  },
  {
    "id": 36,
    "priority": 1,
    "action": { "type": "block" },
    "condition": {
      "urlFilter": "*://*.casalemedia.com/*",
      "excludedResourceTypes": ["main_frame"]
    }
  },
  {
    "id": 37,
    "priority": 1,
    "action": { "type": "block" },
    "condition": {
      "urlFilter": "*://*.contextweb.com/*",
      "excludedResourceTypes": ["main_frame"]
    }
  },
  {
    "id": 38,
    "priority": 1,
    "action": { "type": "block" },
    "condition": {
      "urlFilter": "*://*.mathtag.com/*",
      "excludedResourceTypes": ["main_frame"]
    }
  },
  {
    "id": 39,
    "priority": 1,
    "action": { "type": "block" },
    "condition": {
      "urlFilter": "*://*.bluekai.com/*",
      "excludedResourceTypes": ["main_frame"]
    }
  },
  {
    "id": 40,
    "priority": 1,
    "action": { "type": "block" },
    "condition": {
      "urlFilter": "*://*.crwdcntrl.net/*",
      "excludedResourceTypes": ["main_frame"]
    }
  },
  {
    "id": 41,
    "priority": 1,
    "action": { "type": "block" },
    "condition": {
      "urlFilter": "*://*.demdex.net/*",
      "excludedResourceTypes": ["main_frame"]
    }
  },
  {
    "id": 42,
    "priority": 1,
    "action": { "type": "block" },
    "condition": {
      "urlFilter": "*://*.omtrdc.net/*",
      "excludedResourceTypes": ["main_frame"]
    }
  },
  {
    "id": 43,
    "priority": 1,
    "action": { "type": "block" },
    "condition": {
      "urlFilter": "*://*.2o7.net/*",
      "excludedResourceTypes": ["main_frame"]
    }
  },
  {
    "id": 44,
    "priority": 1,
    "action": { "type": "block" },
    "condition": {
      "urlFilter": "*://*.tiqcdn.com/*",
      "excludedResourceTypes": ["main_frame"]
    }
  },
  {
    "id": 45,
    "priority": 1,
    "action": { "type": "block" },
    "condition": {
      "urlFilter": "*://*.optimizely.com/*",
      "excludedResourceTypes": ["main_frame"]
    }
  },
  {
    "id": 46,
    "priority": 1,
    "action": { "type": "block" },
    "condition": {
      "urlFilter": "*://*.mixpanel.com/*",
      "excludedResourceTypes": ["main_frame"]
    }
  },
  {
    "id": 47,
    "priority": 1,
    "action": { "type": "block" },
    "condition": {
      "urlFilter": "*://*.segment.io/*",
      "excludedResourceTypes": ["main_frame"]
    }
  },
  {
    "id": 48,
    "priority": 1,
    "action": { "type": "block" },
    "condition": {
      "urlFilter": "*://*.segment.com/*",
      "excludedResourceTypes": ["main_frame"]
    }
  },
  {
    "id": 49,
    "priority": 1,
    "action": { "type": "block" },
    "condition": {
      "urlFilter": "*://*.amplitude.com/*",
      "excludedResourceTypes": ["main_frame"]
    }
  },
  {
    "id": 50,
    "priority": 1,
    "action": { "type": "block" },
    "condition": {
      "urlFilter": "*://*.hotjar.com/*",
      "excludedResourceTypes": ["main_frame"]
    }
  },
  {
    "id": 51,
    "priority": 1,
    "action": { "type": "block" },
    "condition": {
      "urlFilter": "*://*.fullstory.com/*",
      "excludedResourceTypes": ["main_frame"]
    }
  },
  {
    "id": 52,
    "priority": 1,
    "action": { "type": "block" },
    "condition": {
      "urlFilter": "*://*.heapanalytics.com/*",
      "excludedResourceTypes": ["main_frame"]
    }
  },
  {
    "id": 53,
    "priority": 1,
    "action": { "type": "block" },
    "condition": {
      "urlFilter": "*://*.logrocket.com/*",
      "excludedResourceTypes": ["main_frame"]
    }
  },
  {
    "id": 54,
    "priority": 1,
    "action": { "type": "block" },
    "condition": {
      "urlFilter": "*://*.adroll.com/*",
      "excludedResourceTypes": ["main_frame"]
    }
  },
  {
    "id": 55,
    "priority": 1,
    "action": { "type": "block" },
    "condition": {
      "urlFilter": "*://*.adroll.net/*",
      "excludedResourceTypes": ["main_frame"]
    }
  },
  {
    "id": 56,
    "priority": 1,
    "action": { "type": "block" },
    "condition": {
      "urlFilter": "*://*.doubleverify.com/*",
      "excludedResourceTypes": ["main_frame"]
    }
  },
  {
    "id": 57,
    "priority": 1,
    "action": { "type": "block" },
    "condition": {
      "urlFilter": "*://*.adsafeprotected.com/*",
      "excludedResourceTypes": ["main_frame"]
    }
  }
]
